tpc182tools/__init__.py
tpc182tools/channelmaps.py
tpc182tools/exceptions.py
tpc182tools/readers.py
tpc182tools/transcoders.py
tpc182tools/utils.py
tpc182tools-1.0.1.dist-info/LICENSE
tpc182tools-1.0.1.dist-info/WHEEL
tpc182tools-1.0.1.dist-info/METADATA
tpc182tools-1.0.1.dist-info/RECORD
