Metadata-Version: 2.3
Name: tpc182tools
Version: 1.0.1
Summary: A collection of useful tools for the TPCs of 182.
Author-email: Alejandro Oranday <alejandro@oran.day>
Requires-Python: >=3.10
Classifier: Programming Language :: Python :: 3
Classifier: License :: OSI Approved :: MIT License
Classifier: Intended Audience :: Science/Research
Requires-Dist: h5py
Requires-Dist: numpy
Project-URL: Home, https://github.com/182-activities/tpc182tools
